Metadata-Version: 2.1
Name: simple-colors-treinalinux
Version: 1.0.0
Summary: Simple colors to terminal
Home-page: https://github.com/treinalinux/simple-colors
Author: Alan da Silva Alves
Author-email: 
License: UNKNOWN
Platform: UNKNOWN
Classifier: Programming Language :: Python :: 3
Classifier: Operating System :: OS Independent
License-File: LICENSE
